flask_iiif/__init__.py
flask_iiif/api.py
flask_iiif/config.py
flask_iiif/decorators.py
flask_iiif/errors.py
flask_iiif/restful.py
flask_iiif/signals.py
flask_iiif/utils.py
flask_iiif/cache/__init__.py
flask_iiif/cache/cache.py
flask_iiif/cache/redis.py
flask_iiif/cache/simple.py
flask_iiif-1.2.1.dist-info/licenses/AUTHORS
flask_iiif-1.2.1.dist-info/licenses/LICENSE
tests/__init__.py
tests/helpers.py
tests/test_context_template.py
tests/test_ext.py
tests/test_image_redis_cache.py
tests/test_image_simple_cache.py
tests/test_multimedia_image_api.py
tests/test_restful_api.py
tests/test_restful_api_signals.py
tests/test_restful_api_with_redis.py
flask_iiif-1.2.1.dist-info/METADATA
flask_iiif-1.2.1.dist-info/WHEEL
flask_iiif-1.2.1.dist-info/top_level.txt
flask_iiif-1.2.1.dist-info/RECORD
