Metadata-Version: 2.4
Name: flask-iiif
Version: 1.2.1
Summary: "Flask-IIIF extension provides easy IIIF API standard integration."
Home-page: http://github.com/inveniosoftware/flask-iiif/
Author: Invenio collaboration
Author-email: info@inveniosoftware.org
License: BSD
Platform: any
Classifier: Development Status :: 5 - Production/Stable
Requires-Python: >=3.7
License-File: LICENSE
License-File: AUTHORS
Requires-Dist: blinker>=1.4
Requires-Dist: cachelib>=0.1
Requires-Dist: Flask>=2.0
Requires-Dist: Flask-RESTful>=0.3.7
Requires-Dist: pillow>=7.0
Requires-Dist: six>=1.7.2
Provides-Extra: tests
Requires-Dist: pytest-black-ng>=0.4.0; extra == "tests"
Requires-Dist: flask-testing>=0.6.0; extra == "tests"
Requires-Dist: pytest-invenio>=1.4.0; extra == "tests"
Requires-Dist: sphinx>=4.5; extra == "tests"
Requires-Dist: redis>=3.5; extra == "tests"
Dynamic: license-file
